next_drop_lib/__init__.py
next_drop_lib/file_receiver.py
next_drop_lib/file_sender.py
next_drop_lib/nextdrop_general.py
next_drop_lib-2.0.1.dist-info/METADATA
next_drop_lib-2.0.1.dist-info/WHEEL
next_drop_lib-2.0.1.dist-info/top_level.txt
next_drop_lib-2.0.1.dist-info/RECORD
